stream_website/__init__.py
stream_website/__main__.py
stream_website/main.py
stream_website/run.py
stream_website/MediaMTX/LICENSE
stream_website/MediaMTX/mediamtx.exe
stream_website/MediaMTX/mediamtx.yml
stream_website/static/index.html
stream_website/static/sitem2.png
stream_website-0.1.5.dist-info/METADATA
stream_website-0.1.5.dist-info/WHEEL
stream_website-0.1.5.dist-info/entry_points.txt
stream_website-0.1.5.dist-info/top_level.txt
stream_website-0.1.5.dist-info/RECORD
