Metadata-Version: 2.4
Name: stream_website
Version: 0.1.5
Summary: One-command streaming website starter
Requires-Python: >=3.9
Requires-Dist: fastapi
Requires-Dist: uvicorn
